printe/__init__.py
printe/hello_world/__init__.py
printe/hello_world/hello_world_diferentes_linguas.py
printe/hello_world/hello_world_original.py
printe/mensagem_propria/__init__.py
printe/mensagem_propria/mensagem.py
pacote_hello_world-0.0.1.dist-info/METADATA
pacote_hello_world-0.0.1.dist-info/WHEEL
pacote_hello_world-0.0.1.dist-info/top_level.txt
pacote_hello_world-0.0.1.dist-info/RECORD
