Metadata-Version: 2.1
Name: pacote-hello-world
Version: 0.0.1
Summary: Print hello world in different languages
Home-page: https://github.com/EmanuelSaimon/pacote-hello-world
Author: Emanuel Saimon
Author-email: esaimon149@gmail.com
Requires-Python: >=3.8
